{"type": "FeatureCollection", "features": [{"id": "50222", "type": "Feature", "properties": {"groupID": 22000.0, "ref_id": "2018_EU_LUCAS_POINT_110", "zoneID": 22095.0, "zone_num": 42}, "geometry": {"type": "Point", "coordinates": [21.9869866666667, 66.0130416666667]}}, {"id": "11062", "type": "Feature", "properties": {"groupID": 22000.0, "ref_id": "2018_EU_LUCAS_POINT_110", "zoneID": 22095.0, "zone_num": 42}, "geometry": {"type": "Point", "coordinates": [26.2745533333333, 66.1283083333333]}}, {"id": "12179", "type": "Feature", "properties": {"groupID": 22000.0, "ref_id": "2018_EU_LUCAS_POINT_110", "zoneID": 22095.0, "zone_num": 42}, "geometry": {"type": "Point", "coordinates": [26.8745216666667, 66.3475566666667]}}], "ids": "9110", "year": "2018", "title": "9110", "name": "9110"}