{"type": "FeatureCollection", "features": [{"id": "48913", "type": "Feature", "properties": {"groupID": 22000.0, "ref_id": "2018_EU_LUCAS_POINT_110", "zoneID": 22190.0, "zone_num": 39}, "geometry": {"type": "Point", "coordinates": [19.52099268, 52.73642714]}}, {"id": "42124", "type": "Feature", "properties": {"groupID": 22000.0, "ref_id": "2018_EU_LUCAS_POINT_110", "zoneID": 22190.0, "zone_num": 39}, "geometry": {"type": "Point", "coordinates": [19.01022148, 51.85336934]}}, {"id": "29821", "type": "Feature", "properties": {"groupID": 22000.0, "ref_id": "2018_EU_LUCAS_POINT_110", "zoneID": 22190.0, "zone_num": 39}, "geometry": {"type": "Point", "coordinates": [21.2179988, 53.04226894]}}, {"id": "43841", "type": "Feature", "properties": {"groupID": 22000.0, "ref_id": "2018_EU_LUCAS_POINT_110", "zoneID": 22190.0, "zone_num": 39}, "geometry": {"type": "Point", "coordinates": [22.87157611, 52.49267716]}}, {"id": "37153", "type": "Feature", "properties": {"groupID": 22000.0, "ref_id": "2018_EU_LUCAS_POINT_110", "zoneID": 22190.0, "zone_num": 39}, "geometry": {"type": "Point", "coordinates": [19.66664929, 50.6781605]}}, {"id": "33026", "type": "Feature", "properties": {"groupID": 46000.0, "ref_id": "2018_EU_LUCAS_POINT_110", "zoneID": 46172.0, "zone_num": 39}, "geometry": {"type": "Point", "coordinates": [8.80434699, 52.60514036]}}, {"id": "14610", "type": "Feature", "properties": {"groupID": 22000.0, "ref_id": "2018_EU_LUCAS_POINT_110", "zoneID": 22190.0, "zone_num": 39}, "geometry": {"type": "Point", "coordinates": [21.15015222, 51.25119183]}}, {"id": "13601", "type": "Feature", "properties": {"groupID": 22000.0, "ref_id": "2018_EU_LUCAS_POINT_110", "zoneID": 22190.0, "zone_num": 39}, "geometry": {"type": "Point", "coordinates": [18.45776223, 53.10570932]}}, {"id": "40263", "type": "Feature", "properties": {"groupID": 22000.0, "ref_id": "2018_EU_LUCAS_POINT_110", "zoneID": 22190.0, "zone_num": 39}, "geometry": {"type": "Point", "coordinates": [13.3514923926479, 51.0348147542041]}}, {"id": "34944", "type": "Feature", "properties": {"groupID": 22000.0, "ref_id": "2018_EU_LUCAS_POINT_110", "zoneID": 22190.0, "zone_num": 39}, "geometry": {"type": "Point", "coordinates": [18.95257695, 51.8577642]}}, {"id": "13800", "type": "Feature", "properties": {"groupID": 22000.0, "ref_id": "2018_EU_LUCAS_POINT_110", "zoneID": 22190.0, "zone_num": 39}, "geometry": {"type": "Point", "coordinates": [21.28805833, 52.96296511]}}, {"id": "50431", "type": "Feature", "properties": {"groupID": 22000.0, "ref_id": "2018_EU_LUCAS_POINT_110", "zoneID": 22190.0, "zone_num": 39}, "geometry": {"type": "Point", "coordinates": [16.41620403, 51.89735427]}}, {"id": "50310", "type": "Feature", "properties": {"groupID": 22000.0, "ref_id": "2018_EU_LUCAS_POINT_110", "zoneID": 22190.0, "zone_num": 39}, "geometry": {"type": "Point", "coordinates": [20.9953267781215, 50.1225767459811]}}, {"id": "25422", "type": "Feature", "properties": {"groupID": 22000.0, "ref_id": "2018_EU_LUCAS_POINT_110", "zoneID": 22190.0, "zone_num": 39}, "geometry": {"type": "Point", "coordinates": [17.73612139, 50.73404863]}}, {"id": "32572", "type": "Feature", "properties": {"groupID": 22000.0, "ref_id": "2018_EU_LUCAS_POINT_110", "zoneID": 22190.0, "zone_num": 39}, "geometry": {"type": "Point", "coordinates": [22.00251906, 49.62023838]}}, {"id": "43734", "type": "Feature", "properties": {"groupID": 22000.0, "ref_id": "2018_EU_LUCAS_POINT_110", "zoneID": 22190.0, "zone_num": 39}, "geometry": {"type": "Point", "coordinates": [19.70402423, 52.21447185]}}, {"id": "21869", "type": "Feature", "properties": {"groupID": 22000.0, "ref_id": "2018_EU_LUCAS_POINT_110", "zoneID": 22190.0, "zone_num": 39}, "geometry": {"type": "Point", "coordinates": [22.79009, 52.00980908]}}, {"id": "42538", "type": "Feature", "properties": {"groupID": 22000.0, "ref_id": "2018_EU_LUCAS_POINT_110", "zoneID": 22190.0, "zone_num": 39}, "geometry": {"type": "Point", "coordinates": [19.71304452, 51.03647584]}}, {"id": "47923", "type": "Feature", "properties": {"groupID": 22000.0, "ref_id": "2018_EU_LUCAS_POINT_110", "zoneID": 22190.0, "zone_num": 39}, "geometry": {"type": "Point", "coordinates": [21.75342488, 51.33681591]}}, {"id": "31113", "type": "Feature", "properties": {"groupID": 22000.0, "ref_id": "2018_EU_LUCAS_POINT_110", "zoneID": 22190.0, "zone_num": 39}, "geometry": {"type": "Point", "coordinates": [22.35132214, 51.71119163]}}, {"id": "23389", "type": "Feature", "properties": {"groupID": 22000.0, "ref_id": "2018_EU_LUCAS_POINT_110", "zoneID": 22190.0, "zone_num": 39}, "geometry": {"type": "Point", "coordinates": [17.37009109, 51.480301]}}, {"id": "23298", "type": "Feature", "properties": {"groupID": 22000.0, "ref_id": "2018_EU_LUCAS_POINT_110", "zoneID": 22190.0, "zone_num": 39}, "geometry": {"type": "Point", "coordinates": [18.97581076, 51.24090954]}}, {"id": "51977", "type": "Feature", "properties": {"groupID": 22000.0, "ref_id": "2018_EU_LUCAS_POINT_110", "zoneID": 22190.0, "zone_num": 39}, "geometry": {"type": "Point", "coordinates": [10.8643332961947, 49.2097228998318]}}, {"id": "40517", "type": "Feature", "properties": {"groupID": 22000.0, "ref_id": "2018_EU_LUCAS_POINT_110", "zoneID": 22190.0, "zone_num": 39}, "geometry": {"type": "Point", "coordinates": [10.9770516, 50.71950851]}}, {"id": "42320", "type": "Feature", "properties": {"groupID": 22000.0, "ref_id": "2018_EU_LUCAS_POINT_110", "zoneID": 22190.0, "zone_num": 39}, "geometry": {"type": "Point", "coordinates": [20.93432715, 52.99586155]}}, {"id": "11009", "type": "Feature", "properties": {"groupID": 22000.0, "ref_id": "2018_EU_LUCAS_POINT_110", "zoneID": 22190.0, "zone_num": 39}, "geometry": {"type": "Point", "coordinates": [19.55245175, 52.60704441]}}, {"id": "36685", "type": "Feature", "properties": {"groupID": 22000.0, "ref_id": "2018_EU_LUCAS_POINT_110", "zoneID": 22190.0, "zone_num": 39}, "geometry": {"type": "Point", "coordinates": [19.04269959, 51.86894971]}}, {"id": "14754", "type": "Feature", "properties": {"groupID": 22000.0, "ref_id": "2018_EU_LUCAS_POINT_110", "zoneID": 22190.0, "zone_num": 39}, "geometry": {"type": "Point", "coordinates": [16.80415259, 53.48109723]}}, {"id": "50794", "type": "Feature", "properties": {"groupID": 22000.0, "ref_id": "2018_EU_LUCAS_POINT_110", "zoneID": 22190.0, "zone_num": 39}, "geometry": {"type": "Point", "coordinates": [19.45757245, 51.89050945]}}, {"id": "39213", "type": "Feature", "properties": {"groupID": 22000.0, "ref_id": "2018_EU_LUCAS_POINT_110", "zoneID": 22190.0, "zone_num": 39}, "geometry": {"type": "Point", "coordinates": [12.02750457, 52.0725006]}}, {"id": "44832", "type": "Feature", "properties": {"groupID": 22000.0, "ref_id": "2018_EU_LUCAS_POINT_110", "zoneID": 22190.0, "zone_num": 39}, "geometry": {"type": "Point", "coordinates": [21.32468469, 51.25237605]}}, {"id": "48434", "type": "Feature", "properties": {"groupID": 46000.0, "ref_id": "2018_EU_LUCAS_POINT_110", "zoneID": 46172.0, "zone_num": 39}, "geometry": {"type": "Point", "coordinates": [3.378788, 49.089467]}}, {"id": "28019", "type": "Feature", "properties": {"groupID": 22000.0, "ref_id": "2018_EU_LUCAS_POINT_110", "zoneID": 22190.0, "zone_num": 39}, "geometry": {"type": "Point", "coordinates": [13.23671583, 52.24344369]}}, {"id": "52538", "type": "Feature", "properties": {"groupID": 22000.0, "ref_id": "2018_EU_LUCAS_POINT_110", "zoneID": 22190.0, "zone_num": 39}, "geometry": {"type": "Point", "coordinates": [16.2441423, 53.58344874]}}, {"id": "36620", "type": "Feature", "properties": {"groupID": 22000.0, "ref_id": "2018_EU_LUCAS_POINT_110", "zoneID": 22190.0, "zone_num": 39}, "geometry": {"type": "Point", "coordinates": [16.42383204, 51.95103731]}}, {"id": "28210", "type": "Feature", "properties": {"groupID": 22000.0, "ref_id": "2018_EU_LUCAS_POINT_110", "zoneID": 22190.0, "zone_num": 39}, "geometry": {"type": "Point", "coordinates": [19.1317725, 52.87537638]}}, {"id": "46538", "type": "Feature", "properties": {"groupID": 22000.0, "ref_id": "2018_EU_LUCAS_POINT_110", "zoneID": 22190.0, "zone_num": 39}, "geometry": {"type": "Point", "coordinates": [19.9273303, 52.81189178]}}, {"id": "11099", "type": "Feature", "properties": {"groupID": 22000.0, "ref_id": "2018_EU_LUCAS_POINT_110", "zoneID": 22190.0, "zone_num": 39}, "geometry": {"type": "Point", "coordinates": [18.34547116, 53.45700335]}}, {"id": "11530", "type": "Feature", "properties": {"groupID": 46000.0, "ref_id": "2018_EU_LUCAS_POINT_110", "zoneID": 46172.0, "zone_num": 39}, "geometry": {"type": "Point", "coordinates": [11.95364451, 53.70978665]}}, {"id": "20209", "type": "Feature", "properties": {"groupID": 22000.0, "ref_id": "2018_EU_LUCAS_POINT_110", "zoneID": 22190.0, "zone_num": 39}, "geometry": {"type": "Point", "coordinates": [19.40099725, 52.03990388]}}, {"id": "27431", "type": "Feature", "properties": {"groupID": 22000.0, "ref_id": "2018_EU_LUCAS_POINT_110", "zoneID": 22190.0, "zone_num": 39}, "geometry": {"type": "Point", "coordinates": [18.97188981, 51.36781641]}}, {"id": "42309", "type": "Feature", "properties": {"groupID": 22000.0, "ref_id": "2018_EU_LUCAS_POINT_110", "zoneID": 22190.0, "zone_num": 39}, "geometry": {"type": "Point", "coordinates": [23.6566686, 51.25486306]}}, {"id": "12845", "type": "Feature", "properties": {"groupID": 22000.0, "ref_id": "2018_EU_LUCAS_POINT_110", "zoneID": 22190.0, "zone_num": 39}, "geometry": {"type": "Point", "coordinates": [15.9764940105379, 50.3340483829379]}}, {"id": "31531", "type": "Feature", "properties": {"groupID": 46000.0, "ref_id": "2018_EU_LUCAS_POINT_110", "zoneID": 46172.0, "zone_num": 39}, "geometry": {"type": "Point", "coordinates": [7.61041, 52.83896]}}, {"id": "49318", "type": "Feature", "properties": {"groupID": 22000.0, "ref_id": "2018_EU_LUCAS_POINT_110", "zoneID": 22190.0, "zone_num": 39}, "geometry": {"type": "Point", "coordinates": [12.51929325, 52.51261001]}}, {"id": "27263", "type": "Feature", "properties": {"groupID": 22000.0, "ref_id": "2018_EU_LUCAS_POINT_110", "zoneID": 22190.0, "zone_num": 39}, "geometry": {"type": "Point", "coordinates": [17.7437823, 53.31635494]}}, {"id": "32516", "type": "Feature", "properties": {"groupID": 46000.0, "ref_id": "2018_EU_LUCAS_POINT_110", "zoneID": 46172.0, "zone_num": 39}, "geometry": {"type": "Point", "coordinates": [7.32362257937376, 52.1852777761543]}}, {"id": "39127", "type": "Feature", "properties": {"groupID": 22000.0, "ref_id": "2018_EU_LUCAS_POINT_110", "zoneID": 22190.0, "zone_num": 39}, "geometry": {"type": "Point", "coordinates": [15.21845526, 53.12741537]}}, {"id": "51765", "type": "Feature", "properties": {"groupID": 22000.0, "ref_id": "2018_EU_LUCAS_POINT_110", "zoneID": 22190.0, "zone_num": 39}, "geometry": {"type": "Point", "coordinates": [18.79008318, 53.55210385]}}, {"id": "21899", "type": "Feature", "properties": {"groupID": 46000.0, "ref_id": "2018_EU_LUCAS_POINT_110", "zoneID": 46172.0, "zone_num": 39}, "geometry": {"type": "Point", "coordinates": [7.99528, 52.86398]}}, {"id": "31776", "type": "Feature", "properties": {"groupID": 22000.0, "ref_id": "2018_EU_LUCAS_POINT_110", "zoneID": 22190.0, "zone_num": 39}, "geometry": {"type": "Point", "coordinates": [18.76576044, 50.4430827]}}, {"id": "38153", "type": "Feature", "properties": {"groupID": 22000.0, "ref_id": "2018_EU_LUCAS_POINT_110", "zoneID": 22190.0, "zone_num": 39}, "geometry": {"type": "Point", "coordinates": [18.64088532, 51.30252817]}}, {"id": "47939", "type": "Feature", "properties": {"groupID": 22000.0, "ref_id": "2018_EU_LUCAS_POINT_110", "zoneID": 22190.0, "zone_num": 39}, "geometry": {"type": "Point", "coordinates": [16.42057077, 52.13155104]}}, {"id": "14159", "type": "Feature", "properties": {"groupID": 22000.0, "ref_id": "2018_EU_LUCAS_POINT_110", "zoneID": 22190.0, "zone_num": 39}, "geometry": {"type": "Point", "coordinates": [12.31411455, 52.53475177]}}, {"id": "20698", "type": "Feature", "properties": {"groupID": 46000.0, "ref_id": "2018_EU_LUCAS_POINT_110", "zoneID": 46172.0, "zone_num": 39}, "geometry": {"type": "Point", "coordinates": [8.46144491806626, 50.569553123787]}}, {"id": "41180", "type": "Feature", "properties": {"groupID": 22000.0, "ref_id": "2018_EU_LUCAS_POINT_110", "zoneID": 22190.0, "zone_num": 39}, "geometry": {"type": "Point", "coordinates": [23.40706495, 52.08652361]}}, {"id": "29273", "type": "Feature", "properties": {"groupID": 22000.0, "ref_id": "2018_EU_LUCAS_POINT_110", "zoneID": 22190.0, "zone_num": 39}, "geometry": {"type": "Point", "coordinates": [10.5692407675087, 49.7871985612437]}}, {"id": "28879", "type": "Feature", "properties": {"groupID": 22000.0, "ref_id": "2018_EU_LUCAS_POINT_110", "zoneID": 22190.0, "zone_num": 39}, "geometry": {"type": "Point", "coordinates": [18.25719026, 51.25812827]}}, {"id": "47867", "type": "Feature", "properties": {"groupID": 22000.0, "ref_id": "2018_EU_LUCAS_POINT_110", "zoneID": 22190.0, "zone_num": 39}, "geometry": {"type": "Point", "coordinates": [18.38193911, 51.46608335]}}, {"id": "20218", "type": "Feature", "properties": {"groupID": 22000.0, "ref_id": "2018_EU_LUCAS_POINT_110", "zoneID": 22190.0, "zone_num": 39}, "geometry": {"type": "Point", "coordinates": [13.3207651879638, 49.3979416368529]}}, {"id": "27195", "type": "Feature", "properties": {"groupID": 22000.0, "ref_id": "2018_EU_LUCAS_POINT_110", "zoneID": 22190.0, "zone_num": 39}, "geometry": {"type": "Point", "coordinates": [19.77857711, 51.88224866]}}, {"id": "41193", "type": "Feature", "properties": {"groupID": 46000.0, "ref_id": "2018_EU_LUCAS_POINT_110", "zoneID": 46172.0, "zone_num": 39}, "geometry": {"type": "Point", "coordinates": [8.6346, 52.36973]}}, {"id": "38643", "type": "Feature", "properties": {"groupID": 46000.0, "ref_id": "2018_EU_LUCAS_POINT_110", "zoneID": 46172.0, "zone_num": 39}, "geometry": {"type": "Point", "coordinates": [10.98817631, 52.57107936]}}, {"id": "26647", "type": "Feature", "properties": {"groupID": 22000.0, "ref_id": "2018_EU_LUCAS_POINT_110", "zoneID": 22190.0, "zone_num": 39}, "geometry": {"type": "Point", "coordinates": [23.26823881, 53.68867774]}}, {"id": "16126", "type": "Feature", "properties": {"groupID": 22000.0, "ref_id": "2018_EU_LUCAS_POINT_110", "zoneID": 22190.0, "zone_num": 39}, "geometry": {"type": "Point", "coordinates": [18.24255112, 50.37348515]}}, {"id": "29496", "type": "Feature", "properties": {"groupID": 22000.0, "ref_id": "2018_EU_LUCAS_POINT_110", "zoneID": 22190.0, "zone_num": 39}, "geometry": {"type": "Point", "coordinates": [14.10618027, 52.45047002]}}, {"id": "35333", "type": "Feature", "properties": {"groupID": 46000.0, "ref_id": "2018_EU_LUCAS_POINT_110", "zoneID": 46172.0, "zone_num": 39}, "geometry": {"type": "Point", "coordinates": [10.40102272, 52.88003409]}}, {"id": "19306", "type": "Feature", "properties": {"groupID": 22000.0, "ref_id": "2018_EU_LUCAS_POINT_110", "zoneID": 22190.0, "zone_num": 39}, "geometry": {"type": "Point", "coordinates": [19.21888748, 51.72851857]}}, {"id": "9206", "type": "Feature", "properties": {"groupID": 22000.0, "ref_id": "2018_EU_LUCAS_POINT_110", "zoneID": 22190.0, "zone_num": 39}, "geometry": {"type": "Point", "coordinates": [18.67820915, 52.85490937]}}, {"id": "12898", "type": "Feature", "properties": {"groupID": 22000.0, "ref_id": "2018_EU_LUCAS_POINT_110", "zoneID": 22190.0, "zone_num": 39}, "geometry": {"type": "Point", "coordinates": [11.96525736, 51.98364928]}}, {"id": "49265", "type": "Feature", "properties": {"groupID": 22000.0, "ref_id": "2018_EU_LUCAS_POINT_110", "zoneID": 22190.0, "zone_num": 39}, "geometry": {"type": "Point", "coordinates": [19.40362854, 49.93969736]}}, {"id": "42474", "type": "Feature", "properties": {"groupID": 22000.0, "ref_id": "2018_EU_LUCAS_POINT_110", "zoneID": 22190.0, "zone_num": 39}, "geometry": {"type": "Point", "coordinates": [21.57484503, 50.86425399]}}, {"id": "39329", "type": "Feature", "properties": {"groupID": 22000.0, "ref_id": "2018_EU_LUCAS_POINT_110", "zoneID": 22190.0, "zone_num": 39}, "geometry": {"type": "Point", "coordinates": [20.63955408, 50.428631]}}, {"id": "39797", "type": "Feature", "properties": {"groupID": 46000.0, "ref_id": "2018_EU_LUCAS_POINT_110", "zoneID": 46172.0, "zone_num": 39}, "geometry": {"type": "Point", "coordinates": [7.16495, 52.37966]}}, {"id": "17125", "type": "Feature", "properties": {"groupID": 22000.0, "ref_id": "2018_EU_LUCAS_POINT_110", "zoneID": 22190.0, "zone_num": 39}, "geometry": {"type": "Point", "coordinates": [14.7231309, 51.04103822]}}, {"id": "9283", "type": "Feature", "properties": {"groupID": 22000.0, "ref_id": "2018_EU_LUCAS_POINT_110", "zoneID": 22190.0, "zone_num": 39}, "geometry": {"type": "Point", "coordinates": [15.41862562, 51.6051804]}}, {"id": "11803", "type": "Feature", "properties": {"groupID": 22000.0, "ref_id": "2018_EU_LUCAS_POINT_110", "zoneID": 22190.0, "zone_num": 39}, "geometry": {"type": "Point", "coordinates": [17.85957738, 52.29730523]}}, {"id": "32739", "type": "Feature", "properties": {"groupID": 22000.0, "ref_id": "2018_EU_LUCAS_POINT_110", "zoneID": 22190.0, "zone_num": 39}, "geometry": {"type": "Point", "coordinates": [14.67122506, 53.32989137]}}, {"id": "37894", "type": "Feature", "properties": {"groupID": 22000.0, "ref_id": "2018_EU_LUCAS_POINT_110", "zoneID": 22190.0, "zone_num": 39}, "geometry": {"type": "Point", "coordinates": [21.35395229, 51.4855966]}}, {"id": "13559", "type": "Feature", "properties": {"groupID": 46000.0, "ref_id": "2018_EU_LUCAS_POINT_110", "zoneID": 46172.0, "zone_num": 39}, "geometry": {"type": "Point", "coordinates": [1.458484, 49.989878]}}, {"id": "28331", "type": "Feature", "properties": {"groupID": 22000.0, "ref_id": "2018_EU_LUCAS_POINT_110", "zoneID": 22190.0, "zone_num": 39}, "geometry": {"type": "Point", "coordinates": [15.45947, 48.77356]}}, {"id": "32379", "type": "Feature", "properties": {"groupID": 22000.0, "ref_id": "2018_EU_LUCAS_POINT_110", "zoneID": 22190.0, "zone_num": 39}, "geometry": {"type": "Point", "coordinates": [20.07105538, 51.22330648]}}, {"id": "12469", "type": "Feature", "properties": {"groupID": 22000.0, "ref_id": "2018_EU_LUCAS_POINT_110", "zoneID": 22190.0, "zone_num": 39}, "geometry": {"type": "Point", "coordinates": [12.13900489, 51.96263639]}}, {"id": "11580", "type": "Feature", "properties": {"groupID": 22000.0, "ref_id": "2018_EU_LUCAS_POINT_110", "zoneID": 22190.0, "zone_num": 39}, "geometry": {"type": "Point", "coordinates": [13.2938943, 52.22388663]}}, {"id": "46198", "type": "Feature", "properties": {"groupID": 22000.0, "ref_id": "2018_EU_LUCAS_POINT_110", "zoneID": 22190.0, "zone_num": 39}, "geometry": {"type": "Point", "coordinates": [15.77737368, 52.14671141]}}, {"id": "35299", "type": "Feature", "properties": {"groupID": 22000.0, "ref_id": "2018_EU_LUCAS_POINT_110", "zoneID": 22190.0, "zone_num": 39}, "geometry": {"type": "Point", "coordinates": [18.41382311, 51.48189543]}}, {"id": "45092", "type": "Feature", "properties": {"groupID": 22000.0, "ref_id": "2018_EU_LUCAS_POINT_110", "zoneID": 22190.0, "zone_num": 39}, "geometry": {"type": "Point", "coordinates": [19.89430685, 53.3219065]}}, {"id": "41124", "type": "Feature", "properties": {"groupID": 22000.0, "ref_id": "2018_EU_LUCAS_POINT_110", "zoneID": 22190.0, "zone_num": 39}, "geometry": {"type": "Point", "coordinates": [16.39233506, 51.93466907]}}, {"id": "40830", "type": "Feature", "properties": {"groupID": 22000.0, "ref_id": "2018_EU_LUCAS_POINT_110", "zoneID": 22190.0, "zone_num": 39}, "geometry": {"type": "Point", "coordinates": [19.40735998, 52.76352992]}}, {"id": "44144", "type": "Feature", "properties": {"groupID": 22000.0, "ref_id": "2018_EU_LUCAS_POINT_110", "zoneID": 22190.0, "zone_num": 39}, "geometry": {"type": "Point", "coordinates": [15.53978736, 52.12206291]}}, {"id": "29832", "type": "Feature", "properties": {"groupID": 22000.0, "ref_id": "2018_EU_LUCAS_POINT_110", "zoneID": 22190.0, "zone_num": 39}, "geometry": {"type": "Point", "coordinates": [20.00142579, 52.35266296]}}, {"id": "11466", "type": "Feature", "properties": {"groupID": 46000.0, "ref_id": "2018_EU_LUCAS_POINT_110", "zoneID": 46172.0, "zone_num": 39}, "geometry": {"type": "Point", "coordinates": [11.43149341, 52.58459458]}}, {"id": "19315", "type": "Feature", "properties": {"groupID": 46000.0, "ref_id": "2018_EU_LUCAS_POINT_110", "zoneID": 46172.0, "zone_num": 39}, "geometry": {"type": "Point", "coordinates": [9.16973014, 53.57881664]}}, {"id": "47571", "type": "Feature", "properties": {"groupID": 22000.0, "ref_id": "2018_EU_LUCAS_POINT_110", "zoneID": 22190.0, "zone_num": 39}, "geometry": {"type": "Point", "coordinates": [21.22916032, 52.96862012]}}, {"id": "19665", "type": "Feature", "properties": {"groupID": 22000.0, "ref_id": "2018_EU_LUCAS_POINT_110", "zoneID": 22190.0, "zone_num": 39}, "geometry": {"type": "Point", "coordinates": [15.20433605, 53.50626303]}}, {"id": "9946", "type": "Feature", "properties": {"groupID": 22000.0, "ref_id": "2018_EU_LUCAS_POINT_110", "zoneID": 22190.0, "zone_num": 39}, "geometry": {"type": "Point", "coordinates": [12.4197646274286, 50.6802516892333]}}, {"id": "51649", "type": "Feature", "properties": {"groupID": 22000.0, "ref_id": "2018_EU_LUCAS_POINT_110", "zoneID": 22190.0, "zone_num": 39}, "geometry": {"type": "Point", "coordinates": [23.22750189, 51.08613682]}}, {"id": "42052", "type": "Feature", "properties": {"groupID": 22000.0, "ref_id": "2018_EU_LUCAS_POINT_110", "zoneID": 22190.0, "zone_num": 39}, "geometry": {"type": "Point", "coordinates": [20.138, 52.55855]}}, {"id": "21650", "type": "Feature", "properties": {"groupID": 46000.0, "ref_id": "2018_EU_LUCAS_POINT_110", "zoneID": 46172.0, "zone_num": 39}, "geometry": {"type": "Point", "coordinates": [10.93684216, 52.93097579]}}, {"id": "31905", "type": "Feature", "properties": {"groupID": 22000.0, "ref_id": "2018_EU_LUCAS_POINT_110", "zoneID": 22190.0, "zone_num": 39}, "geometry": {"type": "Point", "coordinates": [17.370375, 51.660803]}}, {"id": "39704", "type": "Feature", "properties": {"groupID": 22000.0, "ref_id": "2018_EU_LUCAS_POINT_110", "zoneID": 22190.0, "zone_num": 39}, "geometry": {"type": "Point", "coordinates": [15.00643528, 53.62261421]}}, {"id": "9659", "type": "Feature", "properties": {"groupID": 22000.0, "ref_id": "2018_EU_LUCAS_POINT_110", "zoneID": 22190.0, "zone_num": 39}, "geometry": {"type": "Point", "coordinates": [22.33663604, 51.65815852]}}, {"id": "12288", "type": "Feature", "properties": {"groupID": 22000.0, "ref_id": "2018_EU_LUCAS_POINT_110", "zoneID": 22190.0, "zone_num": 39}, "geometry": {"type": "Point", "coordinates": [10.8999779261649, 48.1478880671784]}}, {"id": "41159", "type": "Feature", "properties": {"groupID": 22000.0, "ref_id": "2018_EU_LUCAS_POINT_110", "zoneID": 22190.0, "zone_num": 39}, "geometry": {"type": "Point", "coordinates": [8.74314274638891, 50.5909344367683]}}, {"id": "25103", "type": "Feature", "properties": {"groupID": 46000.0, "ref_id": "2018_EU_LUCAS_POINT_110", "zoneID": 46172.0, "zone_num": 39}, "geometry": {"type": "Point", "coordinates": [7.37959, 52.72623]}}, {"id": "38550", "type": "Feature", "properties": {"groupID": 22000.0, "ref_id": "2018_EU_LUCAS_POINT_110", "zoneID": 22190.0, "zone_num": 39}, "geometry": {"type": "Point", "coordinates": [22.4022889696062, 53.4711124794558]}}, {"id": "23164", "type": "Feature", "properties": {"groupID": 22000.0, "ref_id": "2018_EU_LUCAS_POINT_110", "zoneID": 22190.0, "zone_num": 39}, "geometry": {"type": "Point", "coordinates": [13.86927911, 53.10627128]}}, {"id": "29713", "type": "Feature", "properties": {"groupID": 22000.0, "ref_id": "2018_EU_LUCAS_POINT_110", "zoneID": 22190.0, "zone_num": 39}, "geometry": {"type": "Point", "coordinates": [21.148191, 51.12430498]}}, {"id": "13415", "type": "Feature", "properties": {"groupID": 22000.0, "ref_id": "2018_EU_LUCAS_POINT_110", "zoneID": 22190.0, "zone_num": 39}, "geometry": {"type": "Point", "coordinates": [15.90601078, 50.89653475]}}, {"id": "24579", "type": "Feature", "properties": {"groupID": 46000.0, "ref_id": "2018_EU_LUCAS_POINT_110", "zoneID": 46172.0, "zone_num": 39}, "geometry": {"type": "Point", "coordinates": [8.20087, 52.92118]}}, {"id": "38415", "type": "Feature", "properties": {"groupID": 22000.0, "ref_id": "2018_EU_LUCAS_POINT_110", "zoneID": 22190.0, "zone_num": 39}, "geometry": {"type": "Point", "coordinates": [17.35561088, 52.6365916]}}, {"id": "47399", "type": "Feature", "properties": {"groupID": 22000.0, "ref_id": "2018_EU_LUCAS_POINT_110", "zoneID": 22190.0, "zone_num": 39}, "geometry": {"type": "Point", "coordinates": [18.28269443, 52.03348616]}}, {"id": "13441", "type": "Feature", "properties": {"groupID": 22000.0, "ref_id": "2018_EU_LUCAS_POINT_110", "zoneID": 22190.0, "zone_num": 39}, "geometry": {"type": "Point", "coordinates": [16.246017627418, 49.3816839717329]}}, {"id": "10148", "type": "Feature", "properties": {"groupID": 22000.0, "ref_id": "2018_EU_LUCAS_POINT_110", "zoneID": 22190.0, "zone_num": 39}, "geometry": {"type": "Point", "coordinates": [18.53919, 49.0315]}}, {"id": "53058", "type": "Feature", "properties": {"groupID": 46000.0, "ref_id": "2018_EU_LUCAS_POINT_110", "zoneID": 46172.0, "zone_num": 39}, "geometry": {"type": "Point", "coordinates": [-2.709997, 48.249298]}}, {"id": "25857", "type": "Feature", "properties": {"groupID": 22000.0, "ref_id": "2018_EU_LUCAS_POINT_110", "zoneID": 22190.0, "zone_num": 39}, "geometry": {"type": "Point", "coordinates": [12.57073484, 52.8891491]}}, {"id": "27272", "type": "Feature", "properties": {"groupID": 22000.0, "ref_id": "2018_EU_LUCAS_POINT_110", "zoneID": 22190.0, "zone_num": 39}, "geometry": {"type": "Point", "coordinates": [19.78128085, 51.35676779]}}, {"id": "16794", "type": "Feature", "properties": {"groupID": 22000.0, "ref_id": "2018_EU_LUCAS_POINT_110", "zoneID": 22190.0, "zone_num": 39}, "geometry": {"type": "Point", "coordinates": [13.47210991, 52.25478232]}}, {"id": "30388", "type": "Feature", "properties": {"groupID": 22000.0, "ref_id": "2018_EU_LUCAS_POINT_110", "zoneID": 22190.0, "zone_num": 39}, "geometry": {"type": "Point", "coordinates": [12.30058464, 52.84069918]}}, {"id": "13258", "type": "Feature", "properties": {"groupID": 22000.0, "ref_id": "2018_EU_LUCAS_POINT_110", "zoneID": 22190.0, "zone_num": 39}, "geometry": {"type": "Point", "coordinates": [22.4834757712, 52.4979119631]}}, {"id": "12374", "type": "Feature", "properties": {"groupID": 22000.0, "ref_id": "2018_EU_LUCAS_POINT_110", "zoneID": 22190.0, "zone_num": 39}, "geometry": {"type": "Point", "coordinates": [17.96466205, 50.73628983]}}, {"id": "47633", "type": "Feature", "properties": {"groupID": 22000.0, "ref_id": "2018_EU_LUCAS_POINT_110", "zoneID": 22190.0, "zone_num": 39}, "geometry": {"type": "Point", "coordinates": [21.84864094, 52.25416183]}}, {"id": "36206", "type": "Feature", "properties": {"groupID": 22000.0, "ref_id": "2018_EU_LUCAS_POINT_110", "zoneID": 22190.0, "zone_num": 39}, "geometry": {"type": "Point", "coordinates": [13.4004904, 52.85053964]}}, {"id": "16024", "type": "Feature", "properties": {"groupID": 22000.0, "ref_id": "2018_EU_LUCAS_POINT_110", "zoneID": 22190.0, "zone_num": 39}, "geometry": {"type": "Point", "coordinates": [21.07188102, 51.1679662]}}, {"id": "41098", "type": "Feature", "properties": {"groupID": 22000.0, "ref_id": "2018_EU_LUCAS_POINT_110", "zoneID": 22190.0, "zone_num": 39}, "geometry": {"type": "Point", "coordinates": [15.78693525, 51.76777032]}}, {"id": "55543", "type": "Feature", "properties": {"groupID": 46000.0, "ref_id": "2018_EU_LUCAS_POINT_110", "zoneID": 46172.0, "zone_num": 39}, "geometry": {"type": "Point", "coordinates": [-3.09689252637615, 51.1376017425685]}}, {"id": "27349", "type": "Feature", "properties": {"groupID": 22000.0, "ref_id": "2018_EU_LUCAS_POINT_110", "zoneID": 22190.0, "zone_num": 39}, "geometry": {"type": "Point", "coordinates": [20.47217441, 50.69802737]}}, {"id": "18697", "type": "Feature", "properties": {"groupID": 22000.0, "ref_id": "2018_EU_LUCAS_POINT_110", "zoneID": 22190.0, "zone_num": 39}, "geometry": {"type": "Point", "coordinates": [22.39546386, 51.87027041]}}, {"id": "26070", "type": "Feature", "properties": {"groupID": 22000.0, "ref_id": "2018_EU_LUCAS_POINT_110", "zoneID": 22190.0, "zone_num": 39}, "geometry": {"type": "Point", "coordinates": [19.88533529, 50.49646794]}}, {"id": "47603", "type": "Feature", "properties": {"groupID": 22000.0, "ref_id": "2018_EU_LUCAS_POINT_110", "zoneID": 22190.0, "zone_num": 39}, "geometry": {"type": "Point", "coordinates": [16.41361547, 51.87945411]}}, {"id": "52080", "type": "Feature", "properties": {"groupID": 22000.0, "ref_id": "2018_EU_LUCAS_POINT_110", "zoneID": 22190.0, "zone_num": 39}, "geometry": {"type": "Point", "coordinates": [18.22604153, 52.99531453]}}, {"id": "40652", "type": "Feature", "properties": {"groupID": 22000.0, "ref_id": "2018_EU_LUCAS_POINT_110", "zoneID": 22190.0, "zone_num": 39}, "geometry": {"type": "Point", "coordinates": [18.15905424, 51.35544837]}}, {"id": "43521", "type": "Feature", "properties": {"groupID": 22000.0, "ref_id": "2018_EU_LUCAS_POINT_110", "zoneID": 22190.0, "zone_num": 39}, "geometry": {"type": "Point", "coordinates": [20.61420826, 52.5530933]}}, {"id": "11082", "type": "Feature", "properties": {"groupID": 22000.0, "ref_id": "2018_EU_LUCAS_POINT_110", "zoneID": 22190.0, "zone_num": 39}, "geometry": {"type": "Point", "coordinates": [17.58239167, 53.59747194]}}, {"id": "51737", "type": "Feature", "properties": {"groupID": 22000.0, "ref_id": "2018_EU_LUCAS_POINT_110", "zoneID": 22190.0, "zone_num": 39}, "geometry": {"type": "Point", "coordinates": [18.5873357701287, 51.0171829104124]}}, {"id": "14777", "type": "Feature", "properties": {"groupID": 22000.0, "ref_id": "2018_EU_LUCAS_POINT_110", "zoneID": 22190.0, "zone_num": 39}, "geometry": {"type": "Point", "coordinates": [19.61891229, 52.0947336]}}, {"id": "46985", "type": "Feature", "properties": {"groupID": 22000.0, "ref_id": "2018_EU_LUCAS_POINT_110", "zoneID": 22190.0, "zone_num": 39}, "geometry": {"type": "Point", "coordinates": [13.3668766666667, 53.9488383333333]}}, {"id": "26806", "type": "Feature", "properties": {"groupID": 22000.0, "ref_id": "2018_EU_LUCAS_POINT_110", "zoneID": 22190.0, "zone_num": 39}, "geometry": {"type": "Point", "coordinates": [22.10336075, 51.66446097]}}, {"id": "49095", "type": "Feature", "properties": {"groupID": 22000.0, "ref_id": "2018_EU_LUCAS_POINT_110", "zoneID": 22190.0, "zone_num": 39}, "geometry": {"type": "Point", "coordinates": [19.67933798, 50.87632453]}}, {"id": "32600", "type": "Feature", "properties": {"groupID": 22000.0, "ref_id": "2018_EU_LUCAS_POINT_110", "zoneID": 22190.0, "zone_num": 39}, "geometry": {"type": "Point", "coordinates": [19.46718503, 53.17525315]}}, {"id": "19963", "type": "Feature", "properties": {"groupID": 22000.0, "ref_id": "2018_EU_LUCAS_POINT_110", "zoneID": 22190.0, "zone_num": 39}, "geometry": {"type": "Point", "coordinates": [9.1486341599375, 50.0371955288574]}}, {"id": "16385", "type": "Feature", "properties": {"groupID": 22000.0, "ref_id": "2018_EU_LUCAS_POINT_110", "zoneID": 22190.0, "zone_num": 39}, "geometry": {"type": "Point", "coordinates": [22.7641743700951, 53.45152430702]}}, {"id": "20539", "type": "Feature", "properties": {"groupID": 22000.0, "ref_id": "2018_EU_LUCAS_POINT_110", "zoneID": 22190.0, "zone_num": 39}, "geometry": {"type": "Point", "coordinates": [22.03847486, 53.05333468]}}, {"id": "20314", "type": "Feature", "properties": {"groupID": 22000.0, "ref_id": "2018_EU_LUCAS_POINT_110", "zoneID": 22190.0, "zone_num": 39}, "geometry": {"type": "Point", "coordinates": [19.81204099, 51.4990833]}}, {"id": "52135", "type": "Feature", "properties": {"groupID": 22000.0, "ref_id": "2018_EU_LUCAS_POINT_110", "zoneID": 22190.0, "zone_num": 39}, "geometry": {"type": "Point", "coordinates": [23.5549397, 53.62034418]}}, {"id": "11958", "type": "Feature", "properties": {"groupID": 46000.0, "ref_id": "2018_EU_LUCAS_POINT_110", "zoneID": 46172.0, "zone_num": 39}, "geometry": {"type": "Point", "coordinates": [11.99561576, 53.31356171]}}], "ids": "1600", "year": "2018", "title": "1600", "name": "1600"}