{"type": "FeatureCollection", "features": [{"id": "49442", "type": "Feature", "properties": {"groupID": 46000.0, "ref_id": "2018_EU_LUCAS_POINT_110", "zoneID": 46172.0, "zone_num": 38}, "geometry": {"type": "Point", "coordinates": [8.206459, 45.254804]}}, {"id": "10905", "type": "Feature", "properties": {"groupID": 46000.0, "ref_id": "2018_EU_LUCAS_POINT_110", "zoneID": 46172.0, "zone_num": 38}, "geometry": {"type": "Point", "coordinates": [8.461238, 45.240818]}}, {"id": "23744", "type": "Feature", "properties": {"groupID": 46000.0, "ref_id": "2018_EU_LUCAS_POINT_110", "zoneID": 46172.0, "zone_num": 38}, "geometry": {"type": "Point", "coordinates": [8.310899, 45.166402]}}, {"id": "43866", "type": "Feature", "properties": {"groupID": 46000.0, "ref_id": "2018_EU_LUCAS_POINT_110", "zoneID": 46172.0, "zone_num": 38}, "geometry": {"type": "Point", "coordinates": [11.648473, 45.509564]}}, {"id": "29889", "type": "Feature", "properties": {"groupID": 46000.0, "ref_id": "2018_EU_LUCAS_POINT_110", "zoneID": 46172.0, "zone_num": 38}, "geometry": {"type": "Point", "coordinates": [8.103885, 45.271065]}}, {"id": "34431", "type": "Feature", "properties": {"groupID": 46000.0, "ref_id": "2018_EU_LUCAS_POINT_110", "zoneID": 46172.0, "zone_num": 38}, "geometry": {"type": "Point", "coordinates": [8.130136, 45.253504]}}, {"id": "11738", "type": "Feature", "properties": {"groupID": 46000.0, "ref_id": "2018_EU_LUCAS_POINT_110", "zoneID": 46171.0, "zone_num": 38}, "geometry": {"type": "Point", "coordinates": [25.18036219, 42.65763042]}}, {"id": "45043", "type": "Feature", "properties": {"groupID": 46000.0, "ref_id": "2018_EU_LUCAS_POINT_110", "zoneID": 46172.0, "zone_num": 38}, "geometry": {"type": "Point", "coordinates": [8.437371, 45.186391]}}, {"id": "50207", "type": "Feature", "properties": {"groupID": 46000.0, "ref_id": "2018_EU_LUCAS_POINT_110", "zoneID": 46172.0, "zone_num": 38}, "geometry": {"type": "Point", "coordinates": [9.174409, 45.176728]}}, {"id": "41118", "type": "Feature", "properties": {"groupID": 46000.0, "ref_id": "2018_EU_LUCAS_POINT_110", "zoneID": 46172.0, "zone_num": 38}, "geometry": {"type": "Point", "coordinates": [8.204681, 45.308888]}}, {"id": "48511", "type": "Feature", "properties": {"groupID": 46000.0, "ref_id": "2018_EU_LUCAS_POINT_110", "zoneID": 46172.0, "zone_num": 38}, "geometry": {"type": "Point", "coordinates": [8.380771, 45.383836]}}], "ids": "1300", "year": "2018", "title": "1300", "name": "1300"}